ylem/__init__.py
ylem/cleaner.py
ylem-0.3.1.dist-info/METADATA
ylem-0.3.1.dist-info/WHEEL
ylem-0.3.1.dist-info/entry_points.txt
ylem-0.3.1.dist-info/licenses/LICENSE
ylem-0.3.1.dist-info/RECORD
