Metadata-Version: 2.4
Name: ylem
Version: 0.3.1
Summary: Add your description here
Author-email: Sumuk Shashidhar <sumukuuu@gmail.com>
License-File: LICENSE
Requires-Python: >=3.12
Requires-Dist: hf-transfer>=0.1.9
Requires-Dist: loguru<1,>=0.7.0
Requires-Dist: torch>=2.8.0
Requires-Dist: transformers<5,>=4.40.0
